m3_d15n/__init__.py
m3_d15n/_external_utils.py
m3_d15n/apps.py
m3_d15n/constants.py
m3_d15n/models.py
m3_d15n/signals.py
m3_d15n/utils.py
m3_d15n/migrations/0001_initial.py
m3_d15n/migrations/0002_reinstall.py
m3_d15n/migrations/0003_reinstall.py
m3_d15n/migrations/0004_reinstall.py
m3_d15n/migrations/0005_reinstall.py
m3_d15n/migrations/__init__.py
m3_d15n/sql/main.sql
m3_d15n-1.6.0.dist-info/METADATA
m3_d15n-1.6.0.dist-info/WHEEL
m3_d15n-1.6.0.dist-info/dependency_links.txt
m3_d15n-1.6.0.dist-info/top_level.txt
m3_d15n-1.6.0.dist-info/RECORD
